[
    {
        "name": "Harvard University",
        "min_IELTS": 7.5,
        "max_IELTS": 8.5,
        "min_TOEFL": 107,
        "max_TOEFL": 119,
        "min_GMAT": 716,
        "max_GMAT": 781,
        "min_GRE": 316,
        "max_GRE": 332
    },
    {
        "name": "Stanford University",
        "min_IELTS": 7.5,
        "max_IELTS": 8.5,
        "min_TOEFL": 104,
        "max_TOEFL": 114,
        "min_GMAT": 649,
        "max_GMAT": 782,
        "min_GRE": 300,
        "max_GRE": 339
    },
    {
        "name": "Massachusets Institute of Technology",
        "min_IELTS": 8.0,
        "max_IELTS": 8.5,
        "min_TOEFL": 94,
        "max_TOEFL": 115,
        "min_GMAT": 619,
        "max_GMAT": 765,
        "min_GRE": 317,
        "max_GRE": 340
    },
    {
        "name": "California Institute of Technology",
        "min_IELTS": 7.5,
        "max_IELTS": 8.5,
        "min_TOEFL": 92,
        "max_TOEFL": 113,
        "min_GMAT": 659,
        "max_GMAT": 785,
        "min_GRE": 320,
        "max_GRE": 333
    },
    {
        "name": "University of Oxford",
        "min_IELTS": 8.0,
        "max_IELTS": 8.5,
        "min_TOEFL": 84,
        "max_TOEFL": 112,
        "min_GMAT": 632,
        "max_GMAT": 791,
        "min_GRE": 309,
        "max_GRE": 340
    },
    {
        "name": "University of Cambridge",
        "min_IELTS": 8.5,
        "max_IELTS": 8.5,
        "min_TOEFL": 80,
        "max_TOEFL": 117,
        "min_GMAT": 655,
        "max_GMAT": 752,
        "min_GRE": 303,
        "max_GRE": 330
    },
    {
        "name": "Princeton University",
        "min_IELTS": 7.5,
        "max_IELTS": 8.5,
        "min_TOEFL": 103,
        "max_TOEFL": 120,
        "min_GMAT": 728,
        "max_GMAT": 769,
        "min_GRE": 322,
        "max_GRE": 338
    },
    {
        "name": "Imperial College London",
        "min_IELTS": 7.5,
        "max_IELTS": 8.5,
        "min_TOEFL": 86,
        "max_TOEFL": 111,
        "min_GMAT": 648,
        "max_GMAT": 771,
        "min_GRE": 308,
        "max_GRE": 330
    },
    {
        "name": "University of California, Berkeley",
        "min_IELTS": 7.8,
        "max_IELTS": 8.7,
        "min_TOEFL": 103,
        "max_TOEFL": 112,
        "min_GMAT": 620,
        "max_GMAT": 784,
        "min_GRE": 319,
        "max_GRE": 332
    },
    {
        "name": "Abu Dhabi University",
        "min_IELTS": 8.3,
        "max_IELTS": 8.8,
        "min_TOEFL": 83,
        "max_TOEFL": 117,
        "min_GMAT": 749,
        "max_GMAT": 765,
        "min_GRE": 329,
        "max_GRE": 339
    },
    {
        "name": "Khalifa University",
        "min_IELTS": 6.5,
        "max_IELTS": 8.9,
        "min_TOEFL": 102,
        "max_TOEFL": 119,
        "min_GMAT": 652,
        "max_GMAT": 771,
        "min_GRE": 323,
        "max_GRE": 340
    },
    {
        "name": "New York University, Abu Dhabi",
        "min_IELTS": 8.0,
        "max_IELTS": 8.5,
        "min_TOEFL": 93,
        "max_TOEFL": 120,
        "min_GMAT": 672,
        "max_GMAT": 789,
        "min_GRE": 329,
        "max_GRE": 332
    },
    {
        "name": "Gulf Medical University",
        "min_IELTS": 6.7,
        "max_IELTS": 8.7,
        "min_TOEFL": 99,
        "max_TOEFL": 112,
        "min_GMAT": 650,
        "max_GMAT": 763,
        "min_GRE": 330,
        "max_GRE": 338
    },
    {
        "name": "Abu Dhabi University, Dubai",
        "min_IELTS": 6.5,
        "max_IELTS": 8.8,
        "min_TOEFL": 89,
        "max_TOEFL": 113,
        "min_GMAT": 664,
        "max_GMAT": 775,
        "min_GRE": 312,
        "max_GRE": 339
    },
    {
        "name": "American University in Dubai",
        "min_IELTS": 6.5,
        "max_IELTS": 8.5,
        "min_TOEFL": 80,
        "max_TOEFL": 118,
        "min_GMAT": 698,
        "max_GMAT": 794,
        "min_GRE": 312,
        "max_GRE": 338
    },
    {
        "name": "Amity University Dubai",
        "min_IELTS": 8.4,
        "max_IELTS": 8.5,
        "min_TOEFL": 95,
        "max_TOEFL": 118,
        "min_GMAT": 737,
        "max_GMAT": 777,
        "min_GRE": 318,
        "max_GRE": 330
    },
    {
        "name": "Canadian University Dubai",
        "min_IELTS": 7.3,
        "max_IELTS": 8.8,
        "min_TOEFL": 86,
        "max_TOEFL": 116,
        "min_GMAT": 672,
        "max_GMAT": 752,
        "min_GRE": 314,
        "max_GRE": 330
    },
    {
        "name": "Curtin University",
        "min_IELTS": 7.4,
        "max_IELTS": 8.7,
        "min_TOEFL": 99,
        "max_TOEFL": 111,
        "min_GMAT": 638,
        "max_GMAT": 783,
        "min_GRE": 315,
        "max_GRE": 333
    },
    {
        "name": "Emirates Aviation University",
        "min_IELTS": 6.6,
        "max_IELTS": 8.8,
        "min_TOEFL": 85,
        "max_TOEFL": 114,
        "min_GMAT": 685,
        "max_GMAT": 798,
        "min_GRE": 316,
        "max_GRE": 331
    },
    {
        "name": "Heriot-Watt University",
        "min_IELTS": 8.2,
        "max_IELTS": 8.5,
        "min_TOEFL": 110,
        "max_TOEFL": 118,
        "min_GMAT": 748,
        "max_GMAT": 750,
        "min_GRE": 305,
        "max_GRE": 336
    },
    {
        "name": "Institute of Management Technology - Dubai",
        "min_IELTS": 6.5,
        "max_IELTS": 8.6,
        "min_TOEFL": 99,
        "max_TOEFL": 120,
        "min_GMAT": 700,
        "max_GMAT": 763,
        "min_GRE": 309,
        "max_GRE": 331
    },
    {
        "name": "London Business School",
        "min_IELTS": 8.0,
        "max_IELTS": 8.8,
        "min_TOEFL": 92,
        "max_TOEFL": 117,
        "min_GMAT": 684,
        "max_GMAT": 771,
        "min_GRE": 330,
        "max_GRE": 331
    },
    {
        "name": "Middlesex University Dubai",
        "min_IELTS": 8.4,
        "max_IELTS": 8.7,
        "min_TOEFL": 97,
        "max_TOEFL": 114,
        "min_GMAT": 627,
        "max_GMAT": 780,
        "min_GRE": 324,
        "max_GRE": 337
    },
    {
        "name": "Murdoch University Dubai",
        "min_IELTS": 7.3,
        "max_IELTS": 8.5,
        "min_TOEFL": 91,
        "max_TOEFL": 112,
        "min_GMAT": 705,
        "max_GMAT": 761,
        "min_GRE": 316,
        "max_GRE": 333
    },
    {
        "name": "Rochester Institute of Technology of Dubai",
        "min_IELTS": 8.3,
        "max_IELTS": 8.6,
        "min_TOEFL": 92,
        "max_TOEFL": 117,
        "min_GMAT": 735,
        "max_GMAT": 768,
        "min_GRE": 315,
        "max_GRE": 337
    },
    {
        "name": "University of Birmingham Dubai",
        "min_IELTS": 8.0,
        "max_IELTS": 8.7,
        "min_TOEFL": 95,
        "max_TOEFL": 116,
        "min_GMAT": 670,
        "max_GMAT": 775,
        "min_GRE": 312,
        "max_GRE": 338
    },
    {
        "name": "University of Dubai",
        "min_IELTS": 8.5,
        "max_IELTS": 8.9,
        "min_TOEFL": 88,
        "max_TOEFL": 120,
        "min_GMAT": 673,
        "max_GMAT": 791,
        "min_GRE": 307,
        "max_GRE": 340
    },
    {
        "name": "University of Wollongong in Dubai",
        "min_IELTS": 6.7,
        "max_IELTS": 8.7,
        "min_TOEFL": 110,
        "max_TOEFL": 110,
        "min_GMAT": 603,
        "max_GMAT": 758,
        "min_GRE": 317,
        "max_GRE": 340
    },
    {
        "name": "Australian National University",
        "min_IELTS": 7.6,
        "max_IELTS": 9.0,
        "min_TOEFL": 82,
        "max_TOEFL": 118,
        "min_GMAT": 675,
        "max_GMAT": 783,
        "min_GRE": 325,
        "max_GRE": 331
    },
    {
        "name": "Bond University",
        "min_IELTS": 8.0,
        "max_IELTS": 8.6,
        "min_TOEFL": 94,
        "max_TOEFL": 119,
        "min_GMAT": 717,
        "max_GMAT": 754,
        "min_GRE": 312,
        "max_GRE": 331
    },
    {
        "name": "Central Queensland University",
        "min_IELTS": 7.5,
        "max_IELTS": 8.9,
        "min_TOEFL": 95,
        "max_TOEFL": 116,
        "min_GMAT": 650,
        "max_GMAT": 790,
        "min_GRE": 312,
        "max_GRE": 336
    },
    {
        "name": "Charles Darwin University",
        "min_IELTS": 7.0,
        "max_IELTS": 8.9,
        "min_TOEFL": 93,
        "max_TOEFL": 119,
        "min_GMAT": 645,
        "max_GMAT": 800,
        "min_GRE": 328,
        "max_GRE": 340
    },
    {
        "name": "Charles Stuart University",
        "min_IELTS": 7.2,
        "max_IELTS": 8.6,
        "min_TOEFL": 83,
        "max_TOEFL": 111,
        "min_GMAT": 689,
        "max_GMAT": 794,
        "min_GRE": 301,
        "max_GRE": 332
    },
    {
        "name": "Curtin University",
        "min_IELTS": 7.5,
        "max_IELTS": 8.9,
        "min_TOEFL": 87,
        "max_TOEFL": 114,
        "min_GMAT": 643,
        "max_GMAT": 795,
        "min_GRE": 305,
        "max_GRE": 334
    },
    {
        "name": "Deakin University",
        "min_IELTS": 6.8,
        "max_IELTS": 8.6,
        "min_TOEFL": 95,
        "max_TOEFL": 119,
        "min_GMAT": 697,
        "max_GMAT": 758,
        "min_GRE": 305,
        "max_GRE": 339
    },
    {
        "name": "Edith Cowan University",
        "min_IELTS": 6.7,
        "max_IELTS": 8.7,
        "min_TOEFL": 88,
        "max_TOEFL": 113,
        "min_GMAT": 675,
        "max_GMAT": 787,
        "min_GRE": 315,
        "max_GRE": 336
    },
    {
        "name": "Griffith University",
        "min_IELTS": 8.2,
        "max_IELTS": 8.6,
        "min_TOEFL": 105,
        "max_TOEFL": 116,
        "min_GMAT": 632,
        "max_GMAT": 762,
        "min_GRE": 309,
        "max_GRE": 338
    },
    {
        "name": "James Cook University",
        "min_IELTS": 8.3,
        "max_IELTS": 8.9,
        "min_TOEFL": 106,
        "max_TOEFL": 116,
        "min_GMAT": 713,
        "max_GMAT": 791,
        "min_GRE": 320,
        "max_GRE": 334
    },
    {
        "name": "La Trobe University",
        "min_IELTS": 7.8,
        "max_IELTS": 8.5,
        "min_TOEFL": 101,
        "max_TOEFL": 111,
        "min_GMAT": 614,
        "max_GMAT": 785,
        "min_GRE": 316,
        "max_GRE": 330
    },
    {
        "name": "Monash University",
        "min_IELTS": 8.1,
        "max_IELTS": 8.9,
        "min_TOEFL": 96,
        "max_TOEFL": 120,
        "min_GMAT": 653,
        "max_GMAT": 773,
        "min_GRE": 305,
        "max_GRE": 337
    },
    {
        "name": "Murdoch University",
        "min_IELTS": 7.4,
        "max_IELTS": 8.7,
        "min_TOEFL": 84,
        "max_TOEFL": 111,
        "min_GMAT": 623,
        "max_GMAT": 778,
        "min_GRE": 330,
        "max_GRE": 340
    },
    {
        "name": "The University of Adelaide",
        "min_IELTS": 8.1,
        "max_IELTS": 8.9,
        "min_TOEFL": 95,
        "max_TOEFL": 111,
        "min_GMAT": 635,
        "max_GMAT": 790,
        "min_GRE": 326,
        "max_GRE": 336
    },
    {
        "name": "University of Canberra",
        "min_IELTS": 7.8,
        "max_IELTS": 8.5,
        "min_TOEFL": 87,
        "max_TOEFL": 112,
        "min_GMAT": 628,
        "max_GMAT": 759,
        "min_GRE": 307,
        "max_GRE": 335
    },
    {
        "name": "University of South Australia",
        "min_IELTS": 6.6,
        "max_IELTS": 9.0,
        "min_TOEFL": 84,
        "max_TOEFL": 114,
        "min_GMAT": 720,
        "max_GMAT": 770,
        "min_GRE": 319,
        "max_GRE": 331
    },
    {
        "name": "Victoria University",
        "min_IELTS": 7.4,
        "max_IELTS": 8.7,
        "min_TOEFL": 92,
        "max_TOEFL": 119,
        "min_GMAT": 715,
        "max_GMAT": 774,
        "min_GRE": 330,
        "max_GRE": 338
    },
    {
        "name": "Auckland University of Technology",
        "min_IELTS": 7.8,
        "max_IELTS": 8.8,
        "min_TOEFL": 94,
        "max_TOEFL": 120,
        "min_GMAT": 645,
        "max_GMAT": 753,
        "min_GRE": 310,
        "max_GRE": 331
    },
    {
        "name": "Lincoln University",
        "min_IELTS": 8.5,
        "max_IELTS": 8.6,
        "min_TOEFL": 109,
        "max_TOEFL": 112,
        "min_GMAT": 608,
        "max_GMAT": 794,
        "min_GRE": 314,
        "max_GRE": 333
    },
    {
        "name": "University of Auckland",
        "min_IELTS": 8.3,
        "max_IELTS": 8.5,
        "min_TOEFL": 98,
        "max_TOEFL": 118,
        "min_GMAT": 634,
        "max_GMAT": 789,
        "min_GRE": 324,
        "max_GRE": 340
    },
    {
        "name": "University of Aberdeen",
        "min_IELTS": 6.5,
        "max_IELTS": 8.7,
        "min_TOEFL": 104,
        "max_TOEFL": 110,
        "min_GMAT": 646,
        "max_GMAT": 799,
        "min_GRE": 322,
        "max_GRE": 338
    },
    {
        "name": "Abertay University",
        "min_IELTS": 7.9,
        "max_IELTS": 8.6,
        "min_TOEFL": 110,
        "max_TOEFL": 115,
        "min_GMAT": 692,
        "max_GMAT": 783,
        "min_GRE": 314,
        "max_GRE": 333
    },
    {
        "name": "Anglia Ruskin University",
        "min_IELTS": 8.4,
        "max_IELTS": 8.6,
        "min_TOEFL": 91,
        "max_TOEFL": 113,
        "min_GMAT": 743,
        "max_GMAT": 760,
        "min_GRE": 304,
        "max_GRE": 330
    },
    {
        "name": "Bangor University",
        "min_IELTS": 6.7,
        "max_IELTS": 8.7,
        "min_TOEFL": 106,
        "max_TOEFL": 112,
        "min_GMAT": 742,
        "max_GMAT": 773,
        "min_GRE": 301,
        "max_GRE": 337
    },
    {
        "name": "University of Bath",
        "min_IELTS": 8.3,
        "max_IELTS": 8.6,
        "min_TOEFL": 98,
        "max_TOEFL": 120,
        "min_GMAT": 706,
        "max_GMAT": 750,
        "min_GRE": 320,
        "max_GRE": 340
    },
    {
        "name": "University of Birmingham",
        "min_IELTS": 6.7,
        "max_IELTS": 8.7,
        "min_TOEFL": 94,
        "max_TOEFL": 112,
        "min_GMAT": 633,
        "max_GMAT": 789,
        "min_GRE": 314,
        "max_GRE": 334
    },
    {
        "name": "University of Bolton",
        "min_IELTS": 7.5,
        "max_IELTS": 8.8,
        "min_TOEFL": 110,
        "max_TOEFL": 112,
        "min_GMAT": 704,
        "max_GMAT": 765,
        "min_GRE": 326,
        "max_GRE": 340
    },
    {
        "name": "University of Bradford",
        "min_IELTS": 8.0,
        "max_IELTS": 8.7,
        "min_TOEFL": 90,
        "max_TOEFL": 120,
        "min_GMAT": 643,
        "max_GMAT": 754,
        "min_GRE": 321,
        "max_GRE": 338
    },
    {
        "name": "Brunel University London",
        "min_IELTS": 8.1,
        "max_IELTS": 8.9,
        "min_TOEFL": 94,
        "max_TOEFL": 118,
        "min_GMAT": 709,
        "max_GMAT": 797,
        "min_GRE": 327,
        "max_GRE": 337
    },
    {
        "name": "University of Bristol",
        "min_IELTS": 7.1,
        "max_IELTS": 8.7,
        "min_TOEFL": 91,
        "max_TOEFL": 119,
        "min_GMAT": 634,
        "max_GMAT": 766,
        "min_GRE": 323,
        "max_GRE": 339
    },
    {
        "name": "University of Buckingham",
        "min_IELTS": 7.3,
        "max_IELTS": 8.5,
        "min_TOEFL": 102,
        "max_TOEFL": 116,
        "min_GMAT": 716,
        "max_GMAT": 773,
        "min_GRE": 314,
        "max_GRE": 339
    },
    {
        "name": "Cardiff Metropolitan University",
        "min_IELTS": 8.2,
        "max_IELTS": 8.7,
        "min_TOEFL": 87,
        "max_TOEFL": 111,
        "min_GMAT": 634,
        "max_GMAT": 795,
        "min_GRE": 301,
        "max_GRE": 340
    },
    {
        "name": "De Montfort University",
        "min_IELTS": 8.5,
        "max_IELTS": 8.9,
        "min_TOEFL": 107,
        "max_TOEFL": 118,
        "min_GMAT": 688,
        "max_GMAT": 786,
        "min_GRE": 318,
        "max_GRE": 332
    },
    {
        "name": "University of Dundee",
        "min_IELTS": 7.5,
        "max_IELTS": 8.7,
        "min_TOEFL": 82,
        "max_TOEFL": 114,
        "min_GMAT": 717,
        "max_GMAT": 793,
        "min_GRE": 328,
        "max_GRE": 333
    },
    {
        "name": "University of East Anglia",
        "min_IELTS": 7.9,
        "max_IELTS": 8.8,
        "min_TOEFL": 106,
        "max_TOEFL": 117,
        "min_GMAT": 740,
        "max_GMAT": 766,
        "min_GRE": 305,
        "max_GRE": 332
    },
    {
        "name": "University of East London",
        "min_IELTS": 8.3,
        "max_IELTS": 8.8,
        "min_TOEFL": 105,
        "max_TOEFL": 114,
        "min_GMAT": 681,
        "max_GMAT": 777,
        "min_GRE": 315,
        "max_GRE": 340
    },
    {
        "name": "University of Edinburgh",
        "min_IELTS": 7.9,
        "max_IELTS": 8.6,
        "min_TOEFL": 98,
        "max_TOEFL": 113,
        "min_GMAT": 723,
        "max_GMAT": 778,
        "min_GRE": 305,
        "max_GRE": 339
    },
    {
        "name": "University of Essex",
        "min_IELTS": 8.3,
        "max_IELTS": 8.5,
        "min_TOEFL": 99,
        "max_TOEFL": 112,
        "min_GMAT": 622,
        "max_GMAT": 785,
        "min_GRE": 319,
        "max_GRE": 334
    },
    {
        "name": "University of Exeter",
        "min_IELTS": 8.3,
        "max_IELTS": 8.7,
        "min_TOEFL": 96,
        "max_TOEFL": 112,
        "min_GMAT": 671,
        "max_GMAT": 777,
        "min_GRE": 328,
        "max_GRE": 330
    },
    {
        "name": "University of Glasgow",
        "min_IELTS": 8.0,
        "max_IELTS": 8.6,
        "min_TOEFL": 83,
        "max_TOEFL": 120,
        "min_GMAT": 704,
        "max_GMAT": 756,
        "min_GRE": 304,
        "max_GRE": 334
    },
    {
        "name": "University of Greenwich",
        "min_IELTS": 8.4,
        "max_IELTS": 8.9,
        "min_TOEFL": 91,
        "max_TOEFL": 114,
        "min_GMAT": 698,
        "max_GMAT": 769,
        "min_GRE": 310,
        "max_GRE": 330
    },
    {
        "name": "University of Hertfordshire",
        "min_IELTS": 7.3,
        "max_IELTS": 8.9,
        "min_TOEFL": 105,
        "max_TOEFL": 120,
        "min_GMAT": 641,
        "max_GMAT": 760,
        "min_GRE": 319,
        "max_GRE": 335
    },
    {
        "name": "Kingston University",
        "min_IELTS": 7.0,
        "max_IELTS": 8.7,
        "min_TOEFL": 110,
        "max_TOEFL": 120,
        "min_GMAT": 642,
        "max_GMAT": 759,
        "min_GRE": 321,
        "max_GRE": 332
    },
    {
        "name": "University of Central Lancashire",
        "min_IELTS": 8.4,
        "max_IELTS": 8.8,
        "min_TOEFL": 81,
        "max_TOEFL": 116,
        "min_GMAT": 739,
        "max_GMAT": 784,
        "min_GRE": 314,
        "max_GRE": 331
    },
    {
        "name": "Lancaster University",
        "min_IELTS": 7.8,
        "max_IELTS": 8.5,
        "min_TOEFL": 99,
        "max_TOEFL": 120,
        "min_GMAT": 666,
        "max_GMAT": 788,
        "min_GRE": 328,
        "max_GRE": 336
    },
    {
        "name": "Leeds Trinity University",
        "min_IELTS": 8.0,
        "max_IELTS": 8.8,
        "min_TOEFL": 108,
        "max_TOEFL": 114,
        "min_GMAT": 726,
        "max_GMAT": 784,
        "min_GRE": 321,
        "max_GRE": 340
    },
    {
        "name": "University of Leicester",
        "min_IELTS": 6.6,
        "max_IELTS": 8.7,
        "min_TOEFL": 89,
        "max_TOEFL": 119,
        "min_GMAT": 739,
        "max_GMAT": 794,
        "min_GRE": 315,
        "max_GRE": 332
    },
    {
        "name": "University of Basel",
        "min_IELTS": 7.5,
        "max_IELTS": 8.6,
        "min_TOEFL": 95,
        "max_TOEFL": 120,
        "min_GMAT": 728,
        "max_GMAT": 787,
        "min_GRE": 315,
        "max_GRE": 339
    },
    {
        "name": "University of Bern",
        "min_IELTS": 7.6,
        "max_IELTS": 8.9,
        "min_TOEFL": 83,
        "max_TOEFL": 119,
        "min_GMAT": 632,
        "max_GMAT": 784,
        "min_GRE": 320,
        "max_GRE": 333
    },
    {
        "name": "University of Geneva",
        "min_IELTS": 7.4,
        "max_IELTS": 8.6,
        "min_TOEFL": 92,
        "max_TOEFL": 115,
        "min_GMAT": 724,
        "max_GMAT": 793,
        "min_GRE": 310,
        "max_GRE": 338
    },
    {
        "name": "University of Lausanne",
        "min_IELTS": 6.6,
        "max_IELTS": 8.6,
        "min_TOEFL": 110,
        "max_TOEFL": 120,
        "min_GMAT": 655,
        "max_GMAT": 798,
        "min_GRE": 327,
        "max_GRE": 333
    },
    {
        "name": "University of Lucerne",
        "min_IELTS": 8.2,
        "max_IELTS": 8.7,
        "min_TOEFL": 107,
        "max_TOEFL": 114,
        "min_GMAT": 658,
        "max_GMAT": 787,
        "min_GRE": 318,
        "max_GRE": 336
    },
    {
        "name": "University of Zurich",
        "min_IELTS": 6.7,
        "max_IELTS": 8.5,
        "min_TOEFL": 91,
        "max_TOEFL": 112,
        "min_GMAT": 637,
        "max_GMAT": 765,
        "min_GRE": 315,
        "max_GRE": 335
    },
    {
        "name": "Swiss Federal Institute of Technology Lausanne",
        "min_IELTS": 7.3,
        "max_IELTS": 8.6,
        "min_TOEFL": 95,
        "max_TOEFL": 117,
        "min_GMAT": 620,
        "max_GMAT": 798,
        "min_GRE": 300,
        "max_GRE": 336
    },
    {
        "name": "Swiss Federal Institute of Technology Zurich",
        "min_IELTS": 8.4,
        "max_IELTS": 8.7,
        "min_TOEFL": 106,
        "max_TOEFL": 112,
        "min_GMAT": 658,
        "max_GMAT": 764,
        "min_GRE": 324,
        "max_GRE": 338
    },
    {
        "name": "University of Amsterdam",
        "min_IELTS": 7.5,
        "max_IELTS": 9.0,
        "min_TOEFL": 81,
        "max_TOEFL": 115,
        "min_GMAT": 708,
        "max_GMAT": 779,
        "min_GRE": 303,
        "max_GRE": 331
    },
    {
        "name": "VU University Medical Center",
        "min_IELTS": 6.7,
        "max_IELTS": 8.6,
        "min_TOEFL": 103,
        "max_TOEFL": 110,
        "min_GMAT": 655,
        "max_GMAT": 761,
        "min_GRE": 329,
        "max_GRE": 336
    },
    {
        "name": "Leiden University",
        "min_IELTS": 7.1,
        "max_IELTS": 8.8,
        "min_TOEFL": 102,
        "max_TOEFL": 113,
        "min_GMAT": 728,
        "max_GMAT": 766,
        "min_GRE": 306,
        "max_GRE": 334
    },
    {
        "name": "Radboud University Nijmegen",
        "min_IELTS": 7.7,
        "max_IELTS": 8.6,
        "min_TOEFL": 107,
        "max_TOEFL": 113,
        "min_GMAT": 727,
        "max_GMAT": 765,
        "min_GRE": 316,
        "max_GRE": 330
    },
    {
        "name": "Erasmus University Rotterdam",
        "min_IELTS": 6.6,
        "max_IELTS": 9.0,
        "min_TOEFL": 109,
        "max_TOEFL": 116,
        "min_GMAT": 739,
        "max_GMAT": 793,
        "min_GRE": 304,
        "max_GRE": 339
    },
    {
        "name": "Utrecht University",
        "min_IELTS": 7.4,
        "max_IELTS": 8.9,
        "min_TOEFL": 95,
        "max_TOEFL": 115,
        "min_GMAT": 687,
        "max_GMAT": 766,
        "min_GRE": 319,
        "max_GRE": 336
    },
    {
        "name": "Delft University of Technology",
        "min_IELTS": 8.3,
        "max_IELTS": 8.9,
        "min_TOEFL": 92,
        "max_TOEFL": 119,
        "min_GMAT": 662,
        "max_GMAT": 779,
        "min_GRE": 309,
        "max_GRE": 333
    },
    {
        "name": "University of Twente",
        "min_IELTS": 6.9,
        "max_IELTS": 8.5,
        "min_TOEFL": 97,
        "max_TOEFL": 117,
        "min_GMAT": 723,
        "max_GMAT": 759,
        "min_GRE": 324,
        "max_GRE": 337
    },
    {
        "name": "Protestant Theological University",
        "min_IELTS": 6.7,
        "max_IELTS": 8.6,
        "min_TOEFL": 99,
        "max_TOEFL": 111,
        "min_GMAT": 667,
        "max_GMAT": 799,
        "min_GRE": 321,
        "max_GRE": 330
    },
    {
        "name": "Polytechnic University of the Marches",
        "min_IELTS": 7.4,
        "max_IELTS": 8.6,
        "min_TOEFL": 109,
        "max_TOEFL": 118,
        "min_GMAT": 737,
        "max_GMAT": 788,
        "min_GRE": 320,
        "max_GRE": 340
    },
    {
        "name": "University of Sannio",
        "min_IELTS": 6.8,
        "max_IELTS": 8.9,
        "min_TOEFL": 103,
        "max_TOEFL": 113,
        "min_GMAT": 669,
        "max_GMAT": 794,
        "min_GRE": 312,
        "max_GRE": 336
    },
    {
        "name": "University of Bologna",
        "min_IELTS": 7.5,
        "max_IELTS": 8.5,
        "min_TOEFL": 109,
        "max_TOEFL": 111,
        "min_GMAT": 726,
        "max_GMAT": 784,
        "min_GRE": 307,
        "max_GRE": 337
    },
    {
        "name": "University of Brescia",
        "min_IELTS": 7.0,
        "max_IELTS": 8.6,
        "min_TOEFL": 82,
        "max_TOEFL": 117,
        "min_GMAT": 746,
        "max_GMAT": 787,
        "min_GRE": 311,
        "max_GRE": 339
    },
    {
        "name": "University of Cassino",
        "min_IELTS": 6.7,
        "max_IELTS": 8.7,
        "min_TOEFL": 108,
        "max_TOEFL": 114,
        "min_GMAT": 739,
        "max_GMAT": 764,
        "min_GRE": 309,
        "max_GRE": 335
    },
    {
        "name": "University of Florence",
        "min_IELTS": 6.7,
        "max_IELTS": 9.0,
        "min_TOEFL": 104,
        "max_TOEFL": 111,
        "min_GMAT": 642,
        "max_GMAT": 792,
        "min_GRE": 330,
        "max_GRE": 334
    },
    {
        "name": "University of Macerata",
        "min_IELTS": 8.2,
        "max_IELTS": 8.8,
        "min_TOEFL": 92,
        "max_TOEFL": 117,
        "min_GMAT": 645,
        "max_GMAT": 757,
        "min_GRE": 306,
        "max_GRE": 331
    },
    {
        "name": "University of Messina",
        "min_IELTS": 8.2,
        "max_IELTS": 8.8,
        "min_TOEFL": 81,
        "max_TOEFL": 119,
        "min_GMAT": 685,
        "max_GMAT": 769,
        "min_GRE": 327,
        "max_GRE": 340
    }
]